zftracker/__init__.py
zftracker/dataset.py
zftracker/deprecated.py
zftracker/model.py
zftracker/train.py
zftracker/criterion/__init__.py
zftracker/criterion/classify.py
zftracker/criterion/graph.py
zftracker/criterion/keypoint.py
zftracker/criterion/loss.py
zftracker/criterion/tracking.py
zftracker/inference/__init__.py
zftracker/inference/cover.py
zftracker/inference/keypoint.py
zftracker/inference/model.py
zftracker/inference/pipeline.py
zftracker/inference/trajectory.py
zftracker/inference/trajectory_deprecated.py
zftracker/inference/trajectory_v2.py
zftracker/preprocess/__init__.py
zftracker/preprocess/evaluate_annotation_v1.py
zftracker/preprocess/evaluate_annotation_v2.py
zftracker/preprocess/json.py
zftracker/preprocess/video.py
zftracker/util/__init__.py
zftracker/util/key_frames.py
zftracker/util/nn.py
zftracker/util/pickle.py
zftracker/util/str.py
zftracker/util/tqdm.py
zftracker/util/traj_pool.py
zftracker/util/trivial.py
zftracker/visual/__init__.py
zftracker/visual/images.py
zftracker/visual/plots.py
zftracker/visual/videos.py
zftracker-0.0.8.dist-info/LICENSE.txt
zftracker-0.0.8.dist-info/METADATA
zftracker-0.0.8.dist-info/WHEEL
zftracker-0.0.8.dist-info/top_level.txt
zftracker-0.0.8.dist-info/RECORD
